bongard/__init__.py
bongard/bongard.py
bongard/bongard_painter.py
bongard/plot.py
bongard/util_funcs.py
bongard/sampler/__init__.py
bongard/sampler/abstract_sampler.py
bongard/sampler/basic_sampler.py
bongard/sampler/bongard_sampler.py
bongard/sampler/freeform_sampler.py
bongard-0.0.2.dist-info/LICENSE
bongard-0.0.2.dist-info/METADATA
bongard-0.0.2.dist-info/WHEEL
bongard-0.0.2.dist-info/top_level.txt
bongard-0.0.2.dist-info/RECORD
