Metadata-Version: 2.1
Name: bongard
Version: 0.0.2
Summary: Bongard problem generation using Python turtle graphics.
Home-page: https://github.com/NVlabs/Bongard-LOGO
Author: Lei Mao, Weili Nie
Author-email: lmao@nvidia.com, wnie@nvidia.com
License: UNKNOWN
Platform: UNKNOWN
Classifier: Programming Language :: Python :: 3
Classifier: License :: OSI Approved :: MIT License
Classifier: Operating System :: OS Independent
Requires-Python: >=3.5
Requires-Dist: numpy (>=1.18.3)
Requires-Dist: pillow (>=7.1.2)
Requires-Dist: matplotlib (>=3.2.1)
Requires-Dist: tqdm (>=4.46.0)
Requires-Dist: pandas (==1.0.5)
